[
    {
        "milestone": "0.0.1",
        "list": []
    },
    {
        "milestone": "0.1.0(Production Ready)",
        "list": [
            {
                "title": "address组件异步加载数据",
                "state": "open"
            },
            {
                "title": "step component",
                "state": "open"
            },
            {
                "title": "pull2refresh component",
                "state": "open"
            },
            {
                "title": "Android: demo icon missing",
                "state": "open"
            },
            {
                "title": "Tab: animate bottom border",
                "state": "open"
            },
            {
                "title": "Test on Android",
                "state": "open"
            }
        ]
    }
]